vibeprompt/__init__.py
vibeprompt/audiences/__init__.py
vibeprompt/audiences/adults.py
vibeprompt/audiences/beginners.py
vibeprompt/audiences/business.py
vibeprompt/audiences/children.py
vibeprompt/audiences/developers.py
vibeprompt/audiences/educators.py
vibeprompt/audiences/experts.py
vibeprompt/audiences/general.py
vibeprompt/audiences/healthcare.py
vibeprompt/audiences/intermediates.py
vibeprompt/audiences/professionals.py
vibeprompt/audiences/researchers.py
vibeprompt/audiences/seniors.py
vibeprompt/audiences/students.py
vibeprompt/audiences/teenagers.py
vibeprompt/core/__init__.py
vibeprompt/core/base_styler.py
vibeprompt/core/style_registry.py
vibeprompt/core/llms/__init__.py
vibeprompt/core/llms/anthropic_provider.py
vibeprompt/core/llms/base.py
vibeprompt/core/llms/cohere_provider.py
vibeprompt/core/llms/factory.py
vibeprompt/core/llms/gemini_provider.py
vibeprompt/core/llms/openai_provider.py
vibeprompt/styles/__init__.py
vibeprompt/styles/academic.py
vibeprompt/styles/assertive.py
vibeprompt/styles/authoritative.py
vibeprompt/styles/casual.py
vibeprompt/styles/creative.py
vibeprompt/styles/diplomatic.py
vibeprompt/styles/educational.py
vibeprompt/styles/empathic.py
vibeprompt/styles/formal.py
vibeprompt/styles/friendly.py
vibeprompt/styles/humorous.py
vibeprompt/styles/minimalist.py
vibeprompt/styles/persuasive.py
vibeprompt/styles/playful.py
vibeprompt/styles/poetic.py
vibeprompt/styles/sequential.py
vibeprompt/styles/simple.py
vibeprompt/styles/storytelling.py
vibeprompt/styles/technical.py
vibeprompt/utils/__init__.py
vibeprompt/utils/safety.py
vibeprompt/utils/validation.py
vibeprompt-0.2.5.dist-info/licenses/LICENSE
vibeprompt_cli/__init__.py
vibeprompt_cli/cli_main.py
vibeprompt_cli/config_setup.py
vibeprompt_cli/transform_handler.py
vibeprompt-0.2.5.dist-info/METADATA
vibeprompt-0.2.5.dist-info/WHEEL
vibeprompt-0.2.5.dist-info/entry_points.txt
vibeprompt-0.2.5.dist-info/top_level.txt
vibeprompt-0.2.5.dist-info/RECORD
