Metadata-Version: 2.4
Name: vibeprompt
Version: 0.2.5
Summary: Your words. Their way. Perform style and audience adaptation for your prompts.
Author-email: Mohammed Aly <mohammeda.ebrahim22@gmail.com>
License: MIT
Project-URL: Homepage, https://github.com/mohammedaly22/vibeprompt
Project-URL: Documentation, https://github.com/mohammedaly22/vibeprompt#readme
Project-URL: Source, https://github.com/mohammedaly22/vibeprompt
Keywords: prompt-engineering,langchain,LLM,natural-language-processing,prompt-styling
Classifier: Programming Language :: Python :: 3
Classifier: License :: OSI Approved :: MIT License
Classifier: Operating System :: OS Independent
Classifier: Development Status :: 3 - Alpha
Classifier: Intended Audience :: Developers
Classifier: Topic :: Software Development :: Libraries :: Python Modules
Classifier: Topic :: Scientific/Engineering :: Artificial Intelligence
Requires-Python: >=3.10
License-File: LICENSE
Requires-Dist: aiohappyeyeballs==2.6.1
Requires-Dist: aiohttp==3.12.14
Requires-Dist: aiosignal==1.4.0
Requires-Dist: annotated-types==0.7.0
Requires-Dist: anthropic==0.59.0
Requires-Dist: anyio==4.9.0
Requires-Dist: asttokens==3.0.0
Requires-Dist: async-timeout==4.0.3
Requires-Dist: attrs==25.3.0
Requires-Dist: cachetools==5.5.2
Requires-Dist: certifi==2025.7.14
Requires-Dist: charset-normalizer==3.4.2
Requires-Dist: cohere==5.13.12
Requires-Dist: colorama==0.4.6
Requires-Dist: comm==0.2.2
Requires-Dist: dataclasses-json==0.6.7
Requires-Dist: debugpy==1.8.15
Requires-Dist: decorator==5.2.1
Requires-Dist: distro==1.9.0
Requires-Dist: exceptiongroup==1.3.0
Requires-Dist: executing==2.2.0
Requires-Dist: fastavro==1.11.1
Requires-Dist: filelock==3.18.0
Requires-Dist: filetype==1.2.0
Requires-Dist: frozenlist==1.7.0
Requires-Dist: fsspec==2025.7.0
Requires-Dist: google-ai-generativelanguage==0.6.18
Requires-Dist: google-api-core==2.25.1
Requires-Dist: google-auth==2.40.3
Requires-Dist: googleapis-common-protos==1.70.0
Requires-Dist: greenlet==3.2.3
Requires-Dist: grpcio==1.73.1
Requires-Dist: grpcio-status==1.73.1
Requires-Dist: h11==0.16.0
Requires-Dist: httpcore==1.0.9
Requires-Dist: httpx==0.28.1
Requires-Dist: httpx-sse==0.4.0
Requires-Dist: huggingface-hub==0.33.4
Requires-Dist: idna==3.10
Requires-Dist: ipykernel==6.30.0
Requires-Dist: ipython==8.37.0
Requires-Dist: jedi==0.19.2
Requires-Dist: jiter==0.10.0
Requires-Dist: jsonpatch==1.33
Requires-Dist: jsonpointer==3.0.0
Requires-Dist: jupyter_client==8.6.3
Requires-Dist: jupyter_core==5.8.1
Requires-Dist: langchain==0.3.18
Requires-Dist: langchain-anthropic==0.3.17
Requires-Dist: langchain-cohere==0.4.4
Requires-Dist: langchain-community==0.3.17
Requires-Dist: langchain-core==0.3.71
Requires-Dist: langchain-google-genai==2.1.8
Requires-Dist: langchain-openai==0.3.28
Requires-Dist: langchain-text-splitters==0.3.8
Requires-Dist: langsmith==0.3.45
Requires-Dist: marshmallow==3.26.1
Requires-Dist: matplotlib-inline==0.1.7
Requires-Dist: multidict==6.6.3
Requires-Dist: mypy_extensions==1.1.0
Requires-Dist: nest-asyncio==1.6.0
Requires-Dist: numpy==1.26.4
Requires-Dist: openai==1.97.1
Requires-Dist: orjson==3.11.0
Requires-Dist: packaging==25.0
Requires-Dist: parso==0.8.4
Requires-Dist: platformdirs==4.3.8
Requires-Dist: prompt_toolkit==3.0.51
Requires-Dist: propcache==0.3.2
Requires-Dist: proto-plus==1.26.1
Requires-Dist: protobuf==6.31.1
Requires-Dist: psutil==7.0.0
Requires-Dist: pure_eval==0.2.3
Requires-Dist: pyasn1==0.6.1
Requires-Dist: pyasn1_modules==0.4.2
Requires-Dist: pydantic==2.11.7
Requires-Dist: pydantic-settings==2.10.1
Requires-Dist: pydantic_core==2.33.2
Requires-Dist: Pygments==2.19.2
Requires-Dist: python-dateutil==2.9.0.post0
Requires-Dist: python-dotenv==1.1.1
Requires-Dist: PyYAML==6.0.2
Requires-Dist: pyzmq==27.0.0
Requires-Dist: regex==2024.11.6
Requires-Dist: requests==2.32.4
Requires-Dist: requests-toolbelt==1.0.0
Requires-Dist: rsa==4.9.1
Requires-Dist: six==1.17.0
Requires-Dist: sniffio==1.3.1
Requires-Dist: SQLAlchemy==2.0.41
Requires-Dist: stack-data==0.6.3
Requires-Dist: tenacity==9.1.2
Requires-Dist: tiktoken==0.9.0
Requires-Dist: tokenizers==0.21.2
Requires-Dist: tornado==6.5.1
Requires-Dist: tqdm==4.67.1
Requires-Dist: traitlets==5.14.3
Requires-Dist: types-PyYAML==6.0.12.20250516
Requires-Dist: types-requests==2.32.4.20250611
Requires-Dist: typing-inspect==0.9.0
Requires-Dist: typing-inspection==0.4.1
Requires-Dist: typing_extensions==4.14.1
Requires-Dist: urllib3==2.5.0
Requires-Dist: wcwidth==0.2.13
Requires-Dist: yarl==1.20.1
Requires-Dist: zstandard==0.23.0
Requires-Dist: typer[all]>=0.9.0
Requires-Dist: rich>=13.0.0
Provides-Extra: windows
Requires-Dist: pywin32==311; extra == "windows"
Dynamic: license-file
